setup.cfg
setup.py
compress_react/__init__.py
compress_react/react_compress.py
django_compress_react.egg-info/PKG-INFO
django_compress_react.egg-info/SOURCES.txt
django_compress_react.egg-info/dependency_links.txt
django_compress_react.egg-info/not-zip-safe
django_compress_react.egg-info/requires.txt
django_compress_react.egg-info/top_level.txt