Metadata-Version: 1.1
Name: django-compress-react
Version: 0.0.2
Summary: 
